Workbook

Sheet 汇总看板
A1: 定投汇总看板
A2: 数据来源：各标的记录表 & 每期汇总；本表只读
A4: 一、持仓概览
A5: 标的 | B5: 市场 | C5: 当前期数 | D5: 目标市值 | E5: 当前持仓市值 | F5: 累计净投入 | G5: 浮动盈亏
A6: 沪深300 ETF | B6: A股 | C6: =IFERROR(LOOKUP(2,1/(沪深300!B5:B1000<>""),沪深300!B5:B1000),0) | D6: =IFERROR(LOOKUP(2,1/(沪深300!C5:C1000<>""),沪深300!C5:C1000),0) | E6: =IFERROR(LOOKUP(2,1/(沪深300!H5:H1000<>""),沪深300!H5:H1000),0) | F6: =IFERROR(LOOKUP(2,1/(沪深300!O5:O1000<>""),沪深300!O5:O1000),0) | G6: =IFERROR(LOOKUP(2,1/(沪深300!H5:H1000<>""),沪深300!H5:H1000)-LOOKUP(2,1/(沪深300!O5:O1000<>""),沪深300!O5:O1000),0)
A7: 中证500 ETF | B7: A股 | C7: =IFERROR(LOOKUP(2,1/(中证500!B5:B1000<>""),中证500!B5:B1000),0) | D7: =IFERROR(LOOKUP(2,1/(中证500!C5:C1000<>""),中证500!C5:C1000),0) | E7: =IFERROR(LOOKUP(2,1/(中证500!H5:H1000<>""),中证500!H5:H1000),0) | F7: =IFERROR(LOOKUP(2,1/(中证500!O5:O1000<>""),中证500!O5:O1000),0) | G7: =IFERROR(LOOKUP(2,1/(中证500!H5:H1000<>""),中证500!H5:H1000)-LOOKUP(2,1/(中证500!O5:O1000<>""),中证500!O5:O1000),0)
A8: 恒生指数 ETF | B8: 港股 | C8: =IFERROR(LOOKUP(2,1/(恒生指数!B5:B1000<>""),恒生指数!B5:B1000),0) | D8: =IFERROR(LOOKUP(2,1/(恒生指数!C5:C1000<>""),恒生指数!C5:C1000),0) | E8: =IFERROR(LOOKUP(2,1/(恒生指数!H5:H1000<>""),恒生指数!H5:H1000),0) | F8: =IFERROR(LOOKUP(2,1/(恒生指数!O5:O1000<>""),恒生指数!O5:O1000),0) | G8: =IFERROR(LOOKUP(2,1/(恒生指数!H5:H1000<>""),恒生指数!H5:H1000)-LOOKUP(2,1/(恒生指数!O5:O1000<>""),恒生指数!O5:O1000),0)
A9: 纳指100 ETF | B9: 美股 | C9: =IFERROR(LOOKUP(2,1/(纳指100!B5:B1000<>""),纳指100!B5:B1000),0) | D9: =IFERROR(LOOKUP(2,1/(纳指100!C5:C1000<>""),纳指100!C5:C1000),0) | E9: =IFERROR(LOOKUP(2,1/(纳指100!H5:H1000<>""),纳指100!H5:H1000),0) | F9: =IFERROR(LOOKUP(2,1/(纳指100!O5:O1000<>""),纳指100!O5:O1000),0) | G9: =IFERROR(LOOKUP(2,1/(纳指100!H5:H1000<>""),纳指100!H5:H1000)-LOOKUP(2,1/(纳指100!O5:O1000<>""),纳指100!O5:O1000),0)
A10: 合计 | D10: =SUM(D6:D9) | E10: =SUM(E6:E9) | F10: =SUM(F6:F9) | G10: =SUM(G6:G9)
A12: 二、储备金池 & 阶段
A13: 当前阶段 | B13: =IFERROR(LOOKUP(2,1/(每期汇总!M5:M1000<>""),每期汇总!M5:M1000),"存量阶段")
A14: 储备金池余额 | B14: =IFERROR(LOOKUP(2,1/(每期汇总!K5:K1000<>""),每期汇总!K5:K1000),0)
A15: 四标的累计净投入 | B15: =IFERROR(LOOKUP(2,1/(每期汇总!L5:L1000<>""),每期汇总!L5:L1000),0)
A16: 距触发增量阶段还差 | B16: =MAX(0,参数配置!$C$18-IFERROR(LOOKUP(2,1/(每期汇总!L5:L1000<>""),每期汇总!L5:L1000),0))

Sheet 每期汇总
A1: 每期汇总 — 增量阶段 & 储备金池追踪
A2: 黄色=手动填写 绿色=自动计算 | 存量阶段：自掏腰包买入，收割进储备金；增量阶段：自掏2000/期注入池，买卖均走储备金
A4: 期数 | B4: 日期 | C4: 沪深300 操作(元) | D4: 中证500 操作(元) | E4: 恒生指数 操作(元) | F4: 纳指100 操作(元) | G4: 本期自掏 腰包(元) | H4: 本期增量 注入(元) | I4: 本期收割 入池(元) | J4: 本期从池 支出(元) | K4: 储备金池 余额(元) | L4: 四标的累计 净投入(元) | M4: 当前阶段
A5: 1 | B5: 2026-04-24 | C5: =IFERROR(SUMIF(沪深300!$B$5:$B$1000,A5,沪深300!$L$5:$L$1000),"") | D5: =IFERROR(SUMIF(中证500!$B$5:$B$1000,A5,中证500!$L$5:$L$1000),"") | E5: =IFERROR(SUMIF(恒生指数!$B$5:$B$1000,A5,恒生指数!$L$5:$L$1000),"") | F5: =IFERROR(SUMIF(纳指100!$B$5:$B$1000,A5,纳指100!$L$5:$L$1000),"") | G5: =IFERROR(IF(M5="增量阶段",H5,SUMPRODUCT(MAX(C5,0),1)+SUMPRODUCT(MAX(D5,0),1)+SUMPRODUCT(MAX(E5,0),1)+SUMPRODUCT(MAX(F5,0),1)),"") | H5: 0 | I5: =IFERROR(MAX(-C5,0)+MAX(-D5,0)+MAX(-E5,0)+MAX(-F5,0),"") | J5: =IFERROR(IF(M5="增量阶段",MAX(C5,0)+MAX(D5,0)+MAX(E5,0)+MAX(F5,0),0),"") | K5: =IFERROR(H5+I5-J5,"") | L5: =IFERROR(C5+D5+E5+F5,"") | M5: =IFERROR(IF(L5>=参数配置!$C$18,"增量阶段","存量阶段"),"")
A6: 2 | B6: 2026-05-08 | C6: =IFERROR(SUMIF(沪深300!$B$5:$B$1000,A6,沪深300!$L$5:$L$1000),"") | D6: =IFERROR(SUMIF(中证500!$B$5:$B$1000,A6,中证500!$L$5:$L$1000),"") | E6: =IFERROR(SUMIF(恒生指数!$B$5:$B$1000,A6,恒生指数!$L$5:$L$1000),"") | F6: =IFERROR(SUMIF(纳指100!$B$5:$B$1000,A6,纳指100!$L$5:$L$1000),"") | G6: =IFERROR(IF(M6="增量阶段",H6,SUMPRODUCT(MAX(C6,0),1)+SUMPRODUCT(MAX(D6,0),1)+SUMPRODUCT(MAX(E6,0),1)+SUMPRODUCT(MAX(F6,0),1)),"") | H6: 0 | I6: =IFERROR(MAX(-C6,0)+MAX(-D6,0)+MAX(-E6,0)+MAX(-F6,0),"") | J6: =IFERROR(IF(M6="增量阶段",MAX(C6,0)+MAX(D6,0)+MAX(E6,0)+MAX(F6,0),0),"") | K6: =IFERROR(K5+H6+I6-J6,"") | L6: =IFERROR(L5+C6+D6+E6+F6,"") | M6: =IFERROR(IF(L6>=参数配置!$C$18,"增量阶段","存量阶段"),"")
A7: 3 | B7: 2026-05-22 | C7: =IFERROR(SUMIF(沪深300!$B$5:$B$1000,A7,沪深300!$L$5:$L$1000),"") | D7: =IFERROR(SUMIF(中证500!$B$5:$B$1000,A7,中证500!$L$5:$L$1000),"") | E7: =IFERROR(SUMIF(恒生指数!$B$5:$B$1000,A7,恒生指数!$L$5:$L$1000),"") | F7: =IFERROR(SUMIF(纳指100!$B$5:$B$1000,A7,纳指100!$L$5:$L$1000),"") | G7: =IFERROR(IF(M7="增量阶段",H7,SUMPRODUCT(MAX(C7,0),1)+SUMPRODUCT(MAX(D7,0),1)+SUMPRODUCT(MAX(E7,0),1)+SUMPRODUCT(MAX(F7,0),1)),"") | H7: 0 | I7: =IFERROR(MAX(-C7,0)+MAX(-D7,0)+MAX(-E7,0)+MAX(-F7,0),"") | J7: =IFERROR(IF(M7="增量阶段",MAX(C7,0)+MAX(D7,0)+MAX(E7,0)+MAX(F7,0),0),"") | K7: =IFERROR(K6+H7+I7-J7,"") | L7: =IFERROR(L6+C7+D7+E7+F7,"") | M7: =IFERROR(IF(L7>=参数配置!$C$18,"增量阶段","存量阶段"),"")
C8: =IFERROR(SUMIF(沪深300!$B$5:$B$1000,A8,沪深300!$L$5:$L$1000),"") | D8: =IFERROR(SUMIF(中证500!$B$5:$B$1000,A8,中证500!$L$5:$L$1000),"") | E8: =IFERROR(SUMIF(恒生指数!$B$5:$B$1000,A8,恒生指数!$L$5:$L$1000),"") | F8: =IFERROR(SUMIF(纳指100!$B$5:$B$1000,A8,纳指100!$L$5:$L$1000),"") | G8: =IFERROR(IF(M8="增量阶段",H8,SUMPRODUCT(MAX(C8,0),1)+SUMPRODUCT(MAX(D8,0),1)+SUMPRODUCT(MAX(E8,0),1)+SUMPRODUCT(MAX(F8,0),1)),"") | I8: =IFERROR(MAX(-C8,0)+MAX(-D8,0)+MAX(-E8,0)+MAX(-F8,0),"") | J8: =IFERROR(IF(M8="增量阶段",MAX(C8,0)+MAX(D8,0)+MAX(E8,0)+MAX(F8,0),0),"") | K8: =IFERROR(K7+H8+I8-J8,"") | L8: =IFERROR(L7+C8+D8+E8+F8,"") | M8: =IFERROR(IF(L8>=参数配置!$C$18,"增量阶段","存量阶段"),"")
C9: =IFERROR(SUMIF(沪深300!$B$5:$B$1000,A9,沪深300!$L$5:$L$1000),"") | D9: =IFERROR(SUMIF(中证500!$B$5:$B$1000,A9,中证500!$L$5:$L$1000),"") | E9: =IFERROR(SUMIF(恒生指数!$B$5:$B$1000,A9,恒生指数!$L$5:$L$1000),"") | F9: =IFERROR(SUMIF(纳指100!$B$5:$B$1000,A9,纳指100!$L$5:$L$1000),"") | G9: =IFERROR(IF(M9="增量阶段",H9,SUMPRODUCT(MAX(C9,0),1)+SUMPRODUCT(MAX(D9,0),1)+SUMPRODUCT(MAX(E9,0),1)+SUMPRODUCT(MAX(F9,0),1)),"") | I9: =IFERROR(MAX(-C9,0)+MAX(-D9,0)+MAX(-E9,0)+MAX(-F9,0),"") | J9: =IFERROR(IF(M9="增量阶段",MAX(C9,0)+MAX(D9,0)+MAX(E9,0)+MAX(F9,0),0),"") | K9: =IFERROR(K8+H9+I9-J9,"") | L9: =IFERROR(L8+C9+D9+E9+F9,"") | M9: =IFERROR(IF(L9>=参数配置!$C$18,"增量阶段","存量阶段"),"")
C10: =IFERROR(SUMIF(沪深300!$B$5:$B$1000,A10,沪深300!$L$5:$L$1000),"") | D10: =IFERROR(SUMIF(中证500!$B$5:$B$1000,A10,中证500!$L$5:$L$1000),"") | E10: =IFERROR(SUMIF(恒生指数!$B$5:$B$1000,A10,恒生指数!$L$5:$L$1000),"") | F10: =IFERROR(SUMIF(纳指100!$B$5:$B$1000,A10,纳指100!$L$5:$L$1000),"") | G10: =IFERROR(IF(M10="增量阶段",H10,SUMPRODUCT(MAX(C10,0),1)+SUMPRODUCT(MAX(D10,0),1)+SUMPRODUCT(MAX(E10,0),1)+SUMPRODUCT(MAX(F10,0),1)),"") | I10: =IFERROR(MAX(-C10,0)+MAX(-D10,0)+MAX(-E10,0)+MAX(-F10,0),"") | J10: =IFERROR(IF(M10="增量阶段",MAX(C10,0)+MAX(D10,0)+MAX(E10,0)+MAX(F10,0),0),"") | K10: =IFERROR(K9+H10+I10-J10,"") | L10: =IFERROR(L9+C10+D10+E10+F10,"") | M10: =IFERROR(IF(L10>=参数配置!$C$18,"增量阶段","存量阶段"),"")
C11: =IFERROR(SUMIF(沪深300!$B$5:$B$1000,A11,沪深300!$L$5:$L$1000),"") | D11: =IFERROR(SUMIF(中证500!$B$5:$B$1000,A11,中证500!$L$5:$L$1000),"") | E11: =IFERROR(SUMIF(恒生指数!$B$5:$B$1000,A11,恒生指数!$L$5:$L$1000),"") | F11: =IFERROR(SUMIF(纳指100!$B$5:$B$1000,A11,纳指100!$L$5:$L$1000),"") | G11: =IFERROR(IF(M11="增量阶段",H11,SUMPRODUCT(MAX(C11,0),1)+SUMPRODUCT(MAX(D11,0),1)+SUMPRODUCT(MAX(E11,0),1)+SUMPRODUCT(MAX(F11,0),1)),"") | I11: =IFERROR(MAX(-C11,0)+MAX(-D11,0)+MAX(-E11,0)+MAX(-F11,0),"") | J11: =IFERROR(IF(M11="增量阶段",MAX(C11,0)+MAX(D11,0)+MAX(E11,0)+MAX(F11,0),0),"") | K11: =IFERROR(K10+H11+I11-J11,"") | L11: =IFERROR(L10+C11+D11+E11+F11,"") | M11: =IFERROR(IF(L11>=参数配置!$C$18,"增量阶段","存量阶段"),"")
C12: =IFERROR(SUMIF(沪深300!$B$5:$B$1000,A12,沪深300!$L$5:$L$1000),"") | D12: =IFERROR(SUMIF(中证500!$B$5:$B$1000,A12,中证500!$L$5:$L$1000),"") | E12: =IFERROR(SUMIF(恒生指数!$B$5:$B$1000,A12,恒生指数!$L$5:$L$1000),"") | F12: =IFERROR(SUMIF(纳指100!$B$5:$B$1000,A12,纳指100!$L$5:$L$1000),"") | G12: =IFERROR(IF(M12="增量阶段",H12,SUMPRODUCT(MAX(C12,0),1)+SUMPRODUCT(MAX(D12,0),1)+SUMPRODUCT(MAX(E12,0),1)+SUMPRODUCT(MAX(F12,0),1)),"") | I12: =IFERROR(MAX(-C12,0)+MAX(-D12,0)+MAX(-E12,0)+MAX(-F12,0),"") | J12: =IFERROR(IF(M12="增量阶段",MAX(C12,0)+MAX(D12,0)+MAX(E12,0)+MAX(F12,0),0),"") | K12: =IFERROR(K11+H12+I12-J12,"") | L12: =IFERROR(L11+C12+D12+E12+F12,"") | M12: =IFERROR(IF(L12>=参数配置!$C$18,"增量阶段","存量阶段"),"")
C13: =IFERROR(SUMIF(沪深300!$B$5:$B$1000,A13,沪深300!$L$5:$L$1000),"") | D13: =IFERROR(SUMIF(中证500!$B$5:$B$1000,A13,中证500!$L$5:$L$1000),"") | E13: =IFERROR(SUMIF(恒生指数!$B$5:$B$1000,A13,恒生指数!$L$5:$L$1000),"") | F13: =IFERROR(SUMIF(纳指100!$B$5:$B$1000,A13,纳指100!$L$5:$L$1000),"") | G13: =IFERROR(IF(M13="增量阶段",H13,SUMPRODUCT(MAX(C13,0),1)+SUMPRODUCT(MAX(D13,0),1)+SUMPRODUCT(MAX(E13,0),1)+SUMPRODUCT(MAX(F13,0),1)),"") | I13: =IFERROR(MAX(-C13,0)+MAX(-D13,0)+MAX(-E13,0)+MAX(-F13,0),"") | J13: =IFERROR(IF(M13="增量阶段",MAX(C13,0)+MAX(D13,0)+MAX(E13,0)+MAX(F13,0),0),"") | K13: =IFERROR(K12+H13+I13-J13,"") | L13: =IFERROR(L12+C13+D13+E13+F13,"") | M13: =IFERROR(IF(L13>=参数配置!$C$18,"增量阶段","存量阶段"),"")
C14: =IFERROR(SUMIF(沪深300!$B$5:$B$1000,A14,沪深300!$L$5:$L$1000),"") | D14: =IFERROR(SUMIF(中证500!$B$5:$B$1000,A14,中证500!$L$5:$L$1000),"") | E14: =IFERROR(SUMIF(恒生指数!$B$5:$B$1000,A14,恒生指数!$L$5:$L$1000),"") | F14: =IFERROR(SUMIF(纳指100!$B$5:$B$1000,A14,纳指100!$L$5:$L$1000),"") | G14: =IFERROR(IF(M14="增量阶段",H14,SUMPRODUCT(MAX(C14,0),1)+SUMPRODUCT(MAX(D14,0),1)+SUMPRODUCT(MAX(E14,0),1)+SUMPRODUCT(MAX(F14,0),1)),"") | I14: =IFERROR(MAX(-C14,0)+MAX(-D14,0)+MAX(-E14,0)+MAX(-F14,0),"") | J14: =IFERROR(IF(M14="增量阶段",MAX(C14,0)+MAX(D14,0)+MAX(E14,0)+MAX(F14,0),0),"") | K14: =IFERROR(K13+H14+I14-J14,"") | L14: =IFERROR(L13+C14+D14+E14+F14,"") | M14: =IFERROR(IF(L14>=参数配置!$C$18,"增量阶段","存量阶段"),"")
C15: =IFERROR(SUMIF(沪深300!$B$5:$B$1000,A15,沪深300!$L$5:$L$1000),"") | D15: =IFERROR(SUMIF(中证500!$B$5:$B$1000,A15,中证500!$L$5:$L$1000),"") | E15: =IFERROR(SUMIF(恒生指数!$B$5:$B$1000,A15,恒生指数!$L$5:$L$1000),"") | F15: =IFERROR(SUMIF(纳指100!$B$5:$B$1000,A15,纳指100!$L$5:$L$1000),"") | G15: =IFERROR(IF(M15="增量阶段",H15,SUMPRODUCT(MAX(C15,0),1)+SUMPRODUCT(MAX(D15,0),1)+SUMPRODUCT(MAX(E15,0),1)+SUMPRODUCT(MAX(F15,0),1)),"") | I15: =IFERROR(MAX(-C15,0)+MAX(-D15,0)+MAX(-E15,0)+MAX(-F15,0),"") | J15: =IFERROR(IF(M15="增量阶段",MAX(C15,0)+MAX(D15,0)+MAX(E15,0)+MAX(F15,0),0),"") | K15: =IFERROR(K14+H15+I15-J15,"") | L15: =IFERROR(L14+C15+D15+E15+F15,"") | M15: =IFERROR(IF(L15>=参数配置!$C$18,"增量阶段","存量阶段"),"")
C16: =IFERROR(SUMIF(沪深300!$B$5:$B$1000,A16,沪深300!$L$5:$L$1000),"") | D16: =IFERROR(SUMIF(中证500!$B$5:$B$1000,A16,中证500!$L$5:$L$1000),"") | E16: =IFERROR(SUMIF(恒生指数!$B$5:$B$1000,A16,恒生指数!$L$5:$L$1000),"") | F16: =IFERROR(SUMIF(纳指100!$B$5:$B$1000,A16,纳指100!$L$5:$L$1000),"") | G16: =IFERROR(IF(M16="增量阶段",H16,SUMPRODUCT(MAX(C16,0),1)+SUMPRODUCT(MAX(D16,0),1)+SUMPRODUCT(MAX(E16,0),1)+SUMPRODUCT(MAX(F16,0),1)),"") | I16: =IFERROR(MAX(-C16,0)+MAX(-D16,0)+MAX(-E16,0)+MAX(-F16,0),"") | J16: =IFERROR(IF(M16="增量阶段",MAX(C16,0)+MAX(D16,0)+MAX(E16,0)+MAX(F16,0),0),"") | K16: =IFERROR(K15+H16+I16-J16,"") | L16: =IFERROR(L15+C16+D16+E16+F16,"") | M16: =IFERROR(IF(L16>=参数配置!$C$18,"增量阶段","存量阶段"),"")
C17: =IFERROR(SUMIF(沪深300!$B$5:$B$1000,A17,沪深300!$L$5:$L$1000),"") | D17: =IFERROR(SUMIF(中证500!$B$5:$B$1000,A17,中证500!$L$5:$L$1000),"") | E17: =IFERROR(SUMIF(恒生指数!$B$5:$B$1000,A17,恒生指数!$L$5:$L$1000),"") | F17: =IFERROR(SUMIF(纳指100!$B$5:$B$1000,A17,纳指100!$L$5:$L$1000),"") | G17: =IFERROR(IF(M17="增量阶段",H17,SUMPRODUCT(MAX(C17,0),1)+SUMPRODUCT(MAX(D17,0),1)+SUMPRODUCT(MAX(E17,0),1)+SUMPRODUCT(MAX(F17,0),1)),"") | I17: =IFERROR(MAX(-C17,0)+MAX(-D17,0)+MAX(-E17,0)+MAX(-F17,0),"") | J17: =IFERROR(IF(M17="增量阶段",MAX(C17,0)+MAX(D17,0)+MAX(E17,0)+MAX(F17,0),0),"") | K17: =IFERROR(K16+H17+I17-J17,"") | L17: =IFERROR(L16+C17+D17+E17+F17,"") | M17: =IFERROR(IF(L17>=参数配置!$C$18,"增量阶段","存量阶段"),"")
C18: =IFERROR(SUMIF(沪深300!$B$5:$B$1000,A18,沪深300!$L$5:$L$1000),"") | D18: =IFERROR(SUMIF(中证500!$B$5:$B$1000,A18,中证500!$L$5:$L$1000),"") | E18: =IFERROR(SUMIF(恒生指数!$B$5:$B$1000,A18,恒生指数!$L$5:$L$1000),"") | F18: =IFERROR(SUMIF(纳指100!$B$5:$B$1000,A18,纳指100!$L$5:$L$1000),"") | G18: =IFERROR(IF(M18="增量阶段",H18,SUMPRODUCT(MAX(C18,0),1)+SUMPRODUCT(MAX(D18,0),1)+SUMPRODUCT(MAX(E18,0),1)+SUMPRODUCT(MAX(F18,0),1)),"") | I18: =IFERROR(MAX(-C18,0)+MAX(-D18,0)+MAX(-E18,0)+MAX(-F18,0),"") | J18: =IFERROR(IF(M18="增量阶段",MAX(C18,0)+MAX(D18,0)+MAX(E18,0)+MAX(F18,0),0),"") | K18: =IFERROR(K17+H18+I18-J18,"") | L18: =IFERROR(L17+C18+D18+E18+F18,"") | M18: =IFERROR(IF(L18>=参数配置!$C$18,"增量阶段","存量阶段"),"")
C19: =IFERROR(SUMIF(沪深300!$B$5:$B$1000,A19,沪深300!$L$5:$L$1000),"") | D19: =IFERROR(SUMIF(中证500!$B$5:$B$1000,A19,中证500!$L$5:$L$1000),"") | E19: =IFERROR(SUMIF(恒生指数!$B$5:$B$1000,A19,恒生指数!$L$5:$L$1000),"") | F19: =IFERROR(SUMIF(纳指100!$B$5:$B$1000,A19,纳指100!$L$5:$L$1000),"") | G19: =IFERROR(IF(M19="增量阶段",H19,SUMPRODUCT(MAX(C19,0),1)+SUMPRODUCT(MAX(D19,0),1)+SUMPRODUCT(MAX(E19,0),1)+SUMPRODUCT(MAX(F19,0),1)),"") | I19: =IFERROR(MAX(-C19,0)+MAX(-D19,0)+MAX(-E19,0)+MAX(-F19,0),"") | J19: =IFERROR(IF(M19="增量阶段",MAX(C19,0)+MAX(D19,0)+MAX(E19,0)+MAX(F19,0),0),"") | K19: =IFERROR(K18+H19+I19-J19,"") | L19: =IFERROR(L18+C19+D19+E19+F19,"") | M19: =IFERROR(IF(L19>=参数配置!$C$18,"增量阶段","存量阶段"),"")
... C104: =IFERROR(SUMIF(沪深300!$B$5:$B$1000,A104,沪深300!$L$5:$L$1000),"") | D104: =IFERROR(SUMIF(中证500!$B$5:$B$1000,A104,中证500!$L$5:$L$1000),"") | E104: =IFERROR(SUMIF(恒生指数!$B$5:$B$1000,A104,恒生指数!$L$5:$L$1000),"") | F104: =IFERROR(SUMIF(纳指100!$B$5:$B$1000,A104,纳指100!$L$5:$L$1000),"") | G104: =IFERROR(IF(M104="增量阶段",H104,SUMPRODUCT(MAX(C104,0),1)+SUMPRODUCT(MAX(D104,0),1)+SUMPRODUCT(MAX(E104,0),1)+SUMPRODUCT(MAX(F104,0),1)),"") | I104: =IFERROR(MAX(-C104,0)+MAX(-D104,0)+MAX(-E104,0)+MAX(-F104,0),"") | J104: =IFERROR(IF(M104="增量阶段",MAX(C104,0)+MAX(D104,0)+MAX(E104,0)+MAX(F104,0),0),"") | K104: =IFERROR(K103+H104+I104-J104,"") | L104: =IFERROR(L103+C104+D104+E104+F104,"") | M104: =IFERROR(IF(L104>=参数配置!$C$18,"增量阶段","存量阶段"),"")

Sheet 参数配置
A1: 定投策略参数配置（修改此表，所有记录表自动更新）
A2: 黄色单元格可修改；绿色为只读说明
A4: 标的配比 | B4: 标的名称 | C4: 市场 | D4: 基准金额(元) | E4: 权重
A5: 沪深300 ETF | B5: A股 | C5: 1500 | D5: 0.25
A6: 中证500 ETF | B6: A股 | C6: 1500 | D6: 0.25
A7: 恒生指数 ETF | B7: 港股 | C7: 600 | D7: 0.1
A8: 纳指100 ETF | B8: 美股 | C8: 2400 | D8: 0.4
A9: 合计 | C9: =SUM(C5:C8) | D9: =SUM(D5:D8)
A11: 清仓参数 | B11: 标的 | C11: 阈值 | D11: 说明
A12: 全仓清仓偏离度阈值 | B12: 沪深300 ETF | C12: 0.5 | D12: 偏离度超 +50%，全部清仓并进入冷却期
B13: 中证500 ETF | C13: 0.5
B14: 恒生指数 ETF | C14: 0.35
B15: 纳指100 ETF | C15: 0.3
A17: 三、增量阶段
A18: 触发门槛（累计净投入） | C18: 150000 | D18: 达到后切换为增量阶段，买卖均走储备金池
A19: 每期增量注入金额 | C19: 2000 | D19: 每期向储备金池注入的新增资金

Sheet 沪深300
A1: 沪深300 ETF — 定投追踪记录
A2: 黄色=手动填写 绿色=自动计算 蓝色=建议参考（可覆盖）
A3: 手动填写 | B3: 自动计算 | C3: 建议参考 | R3: 期数偏移: | S3: 0
A4: 日期 | B4: 期数 | C4: 目标市值 | D4: 当前价格 | E4: 250日均线 | F4: 均线偏离度 | G4: 持仓份额 | H4: 持仓市值 | I4: 建议操作金额 | J4: 建议操作 | K4: 建议金额 | L4: 实际操作(元) | M4: 买卖份额 | N4: 操作后份额 | O4: 累计净投入 | P4: 储备金± | Q4: 备注
A5: 2026-04-24 | B5: 1 | C5: =IFERROR(参数配置!$C$5*(B5-$S$3),"") | D5: 4.774 | E5: 4.3435 | F5: =IFERROR((D5-E5)/E5,"") | G5: 0 | H5: =IFERROR(G5*D5,"") | I5: =IFERROR(IF(F5>=参数配置!$C$12,-H5,C5-H5),"") | J5: =IFERROR(IF(F5>=参数配置!$C$12,"全仓清仓",IF(H5>C5,"卖出超额","正常定投")),"") | K5: =IFERROR(I5,"") | L5: 1432.2 | M5: 300 | N5: =IFERROR(G5+M5,"") | O5: =IFERROR(L5,"") | P5: =IFERROR(-L5,"")
A6: 2026-05-08 | B6: 2 | C6: =IFERROR(参数配置!$C$5*(B6-$S$3),"") | D6: 4.893 | E6: 4.3754 | F6: =IFERROR((D6-E6)/E6,"") | G6: 300 | H6: =IFERROR(G6*D6,"") | I6: =IFERROR(IF(F6>=参数配置!$C$12,-H6,C6-H6),"") | J6: =IFERROR(IF(F6>=参数配置!$C$12,"全仓清仓",IF(H6>C6,"卖出超额","正常定投")),"") | K6: =IFERROR(I6,"") | L6: 1467.9 | M6: 300 | N6: =IFERROR(G6+M6,"") | O6: =IFERROR(O5+L6,"") | P6: =IFERROR(-L6,"")
A7: 2026-05-22 | B7: 3 | C7: =IFERROR(参数配置!$C$5*(B7-$S$3),"") | D7: 4.828 | E7: 4.4239 | F7: =IFERROR((D7-E7)/E7,"") | G7: 600 | H7: =IFERROR(G7*D7,"") | I7: =IFERROR(IF(F7>=参数配置!$C$12,-H7,C7-H7),"") | J7: =IFERROR(IF(F7>=参数配置!$C$12,"全仓清仓",IF(H7>C7,"卖出超额","正常定投")),"") | K7: =IFERROR(I7,"") | L7: 1448.4 | M7: 300 | N7: =IFERROR(G7+M7,"") | O7: =IFERROR(O6+L7,"") | P7: =IFERROR(-L7,"")
C8: =IFERROR(参数配置!$C$5*(B8-$S$3),"") | F8: =IFERROR((D8-E8)/E8,"") | H8: =IFERROR(G8*D8,"") | I8: =IFERROR(IF(F8>=参数配置!$C$12,-H8,C8-H8),"") | J8: =IFERROR(IF(F8>=参数配置!$C$12,"全仓清仓",IF(H8>C8,"卖出超额","正常定投")),"") | K8: =IFERROR(I8,"") | N8: =IFERROR(G8+M8,"") | O8: =IFERROR(O7+L8,"") | P8: =IFERROR(-L8,"")
C9: =IFERROR(参数配置!$C$5*(B9-$S$3),"") | F9: =IFERROR((D9-E9)/E9,"") | H9: =IFERROR(G9*D9,"") | I9: =IFERROR(IF(F9>=参数配置!$C$12,-H9,C9-H9),"") | J9: =IFERROR(IF(F9>=参数配置!$C$12,"全仓清仓",IF(H9>C9,"卖出超额","正常定投")),"") | K9: =IFERROR(I9,"") | N9: =IFERROR(G9+M9,"") | O9: =IFERROR(O8+L9,"") | P9: =IFERROR(-L9,"")
C10: =IFERROR(参数配置!$C$5*(B10-$S$3),"") | F10: =IFERROR((D10-E10)/E10,"") | H10: =IFERROR(G10*D10,"") | I10: =IFERROR(IF(F10>=参数配置!$C$12,-H10,C10-H10),"") | J10: =IFERROR(IF(F10>=参数配置!$C$12,"全仓清仓",IF(H10>C10,"卖出超额","正常定投")),"") | K10: =IFERROR(I10,"") | N10: =IFERROR(G10+M10,"") | O10: =IFERROR(O9+L10,"") | P10: =IFERROR(-L10,"")
C11: =IFERROR(参数配置!$C$5*(B11-$S$3),"") | F11: =IFERROR((D11-E11)/E11,"") | H11: =IFERROR(G11*D11,"") | I11: =IFERROR(IF(F11>=参数配置!$C$12,-H11,C11-H11),"") | J11: =IFERROR(IF(F11>=参数配置!$C$12,"全仓清仓",IF(H11>C11,"卖出超额","正常定投")),"") | K11: =IFERROR(I11,"") | N11: =IFERROR(G11+M11,"") | O11: =IFERROR(O10+L11,"") | P11: =IFERROR(-L11,"")
C12: =IFERROR(参数配置!$C$5*(B12-$S$3),"") | F12: =IFERROR((D12-E12)/E12,"") | H12: =IFERROR(G12*D12,"") | I12: =IFERROR(IF(F12>=参数配置!$C$12,-H12,C12-H12),"") | J12: =IFERROR(IF(F12>=参数配置!$C$12,"全仓清仓",IF(H12>C12,"卖出超额","正常定投")),"") | K12: =IFERROR(I12,"") | N12: =IFERROR(G12+M12,"") | O12: =IFERROR(O11+L12,"") | P12: =IFERROR(-L12,"")
C13: =IFERROR(参数配置!$C$5*(B13-$S$3),"") | F13: =IFERROR((D13-E13)/E13,"") | H13: =IFERROR(G13*D13,"") | I13: =IFERROR(IF(F13>=参数配置!$C$12,-H13,C13-H13),"") | J13: =IFERROR(IF(F13>=参数配置!$C$12,"全仓清仓",IF(H13>C13,"卖出超额","正常定投")),"") | K13: =IFERROR(I13,"") | N13: =IFERROR(G13+M13,"") | O13: =IFERROR(O12+L13,"") | P13: =IFERROR(-L13,"")
C14: =IFERROR(参数配置!$C$5*(B14-$S$3),"") | F14: =IFERROR((D14-E14)/E14,"") | H14: =IFERROR(G14*D14,"") | I14: =IFERROR(IF(F14>=参数配置!$C$12,-H14,C14-H14),"") | J14: =IFERROR(IF(F14>=参数配置!$C$12,"全仓清仓",IF(H14>C14,"卖出超额","正常定投")),"") | K14: =IFERROR(I14,"") | N14: =IFERROR(G14+M14,"") | O14: =IFERROR(O13+L14,"") | P14: =IFERROR(-L14,"")
C15: =IFERROR(参数配置!$C$5*(B15-$S$3),"") | F15: =IFERROR((D15-E15)/E15,"") | H15: =IFERROR(G15*D15,"") | I15: =IFERROR(IF(F15>=参数配置!$C$12,-H15,C15-H15),"") | J15: =IFERROR(IF(F15>=参数配置!$C$12,"全仓清仓",IF(H15>C15,"卖出超额","正常定投")),"") | K15: =IFERROR(I15,"") | N15: =IFERROR(G15+M15,"") | O15: =IFERROR(O14+L15,"") | P15: =IFERROR(-L15,"")
C16: =IFERROR(参数配置!$C$5*(B16-$S$3),"") | F16: =IFERROR((D16-E16)/E16,"") | H16: =IFERROR(G16*D16,"") | I16: =IFERROR(IF(F16>=参数配置!$C$12,-H16,C16-H16),"") | J16: =IFERROR(IF(F16>=参数配置!$C$12,"全仓清仓",IF(H16>C16,"卖出超额","正常定投")),"") | K16: =IFERROR(I16,"") | N16: =IFERROR(G16+M16,"") | O16: =IFERROR(O15+L16,"") | P16: =IFERROR(-L16,"")
C17: =IFERROR(参数配置!$C$5*(B17-$S$3),"") | F17: =IFERROR((D17-E17)/E17,"") | H17: =IFERROR(G17*D17,"") | I17: =IFERROR(IF(F17>=参数配置!$C$12,-H17,C17-H17),"") | J17: =IFERROR(IF(F17>=参数配置!$C$12,"全仓清仓",IF(H17>C17,"卖出超额","正常定投")),"") | K17: =IFERROR(I17,"") | N17: =IFERROR(G17+M17,"") | O17: =IFERROR(O16+L17,"") | P17: =IFERROR(-L17,"")
C18: =IFERROR(参数配置!$C$5*(B18-$S$3),"") | F18: =IFERROR((D18-E18)/E18,"") | H18: =IFERROR(G18*D18,"") | I18: =IFERROR(IF(F18>=参数配置!$C$12,-H18,C18-H18),"") | J18: =IFERROR(IF(F18>=参数配置!$C$12,"全仓清仓",IF(H18>C18,"卖出超额","正常定投")),"") | K18: =IFERROR(I18,"") | N18: =IFERROR(G18+M18,"") | O18: =IFERROR(O17+L18,"") | P18: =IFERROR(-L18,"")
C19: =IFERROR(参数配置!$C$5*(B19-$S$3),"") | F19: =IFERROR((D19-E19)/E19,"") | H19: =IFERROR(G19*D19,"") | I19: =IFERROR(IF(F19>=参数配置!$C$12,-H19,C19-H19),"") | J19: =IFERROR(IF(F19>=参数配置!$C$12,"全仓清仓",IF(H19>C19,"卖出超额","正常定投")),"") | K19: =IFERROR(I19,"") | N19: =IFERROR(G19+M19,"") | O19: =IFERROR(O18+L19,"") | P19: =IFERROR(-L19,"")
... C104: =IFERROR(参数配置!$C$5*(B104-$S$3),"") | F104: =IFERROR((D104-E104)/E104,"") | H104: =IFERROR(G104*D104,"") | I104: =IFERROR(IF(F104>=参数配置!$C$12,-H104,C104-H104),"") | J104: =IFERROR(IF(F104>=参数配置!$C$12,"全仓清仓",IF(H104>C104,"卖出超额","正常定投")),"") | K104: =IFERROR(I104,"") | N104: =IFERROR(G104+M104,"") | O104: =IFERROR(O103+L104,"") | P104: =IFERROR(-L104,"")

Sheet 中证500
A1: 中证500 ETF — 定投追踪记录
A2: 黄色=手动填写 绿色=自动计算 蓝色=建议参考（可覆盖）
A3: 手动填写 | B3: 自动计算 | C3: 建议参考 | R3: 期数偏移: | S3: 0
A4: 日期 | B4: 期数 | C4: 目标市值 | D4: 当前价格 | E4: 250日均线 | F4: 均线偏离度 | G4: 持仓份额 | H4: 持仓市值 | I4: 建议操作金额 | J4: 建议操作 | K4: 建议金额 | L4: 实际操作(元) | M4: 买卖份额 | N4: 操作后份额 | O4: 累计净投入 | P4: 储备金± | Q4: 备注
A5: 2026-04-24 | B5: 1 | C5: =IFERROR(参数配置!$C$6*(B5-$S$3),"") | D5: 8.302 | E5: 7.0208 | F5: =IFERROR((D5-E5)/E5,"") | G5: 0 | H5: =IFERROR(G5*D5,"") | I5: =IFERROR(IF(F5>=参数配置!$C$13,-H5,C5-H5),"") | J5: =IFERROR(IF(F5>=参数配置!$C$13,"全仓清仓",IF(H5>C5,"卖出超额","正常定投")),"") | K5: =IFERROR(I5,"") | L5: 830.2 | M5: 100 | N5: =IFERROR(G5+M5,"") | O5: =IFERROR(L5,"") | P5: =IFERROR(-L5,"")
A6: 2026-05-08 | B6: 2 | C6: =IFERROR(参数配置!$C$6*(B6-$S$3),"") | D6: 8.768 | E6: 7.1015 | F6: =IFERROR((D6-E6)/E6,"") | G6: 100 | H6: =IFERROR(G6*D6,"") | I6: =IFERROR(IF(F6>=参数配置!$C$13,-H6,C6-H6),"") | J6: =IFERROR(IF(F6>=参数配置!$C$13,"全仓清仓",IF(H6>C6,"卖出超额","正常定投")),"") | K6: =IFERROR(I6,"") | L6: 1753.6 | M6: 200 | N6: =IFERROR(G6+M6,"") | O6: =IFERROR(O5+L6,"") | P6: =IFERROR(-L6,"")
A7: 2026-05-22 | B7: 3 | C7: =IFERROR(参数配置!$C$6*(B7-$S$3),"") | D7: 8.576 | E7: 7.2287 | F7: =IFERROR((D7-E7)/E7,"") | G7: 300 | H7: =IFERROR(G7*D7,"") | I7: =IFERROR(IF(F7>=参数配置!$C$13,-H7,C7-H7),"") | J7: =IFERROR(IF(F7>=参数配置!$C$13,"全仓清仓",IF(H7>C7,"卖出超额","正常定投")),"") | K7: =IFERROR(I7,"") | L7: 1715.2 | M7: 200 | N7: =IFERROR(G7+M7,"") | O7: =IFERROR(O6+L7,"") | P7: =IFERROR(-L7,"")
C8: =IFERROR(参数配置!$C$6*(B8-$S$3),"") | F8: =IFERROR((D8-E8)/E8,"") | H8: =IFERROR(G8*D8,"") | I8: =IFERROR(IF(F8>=参数配置!$C$13,-H8,C8-H8),"") | J8: =IFERROR(IF(F8>=参数配置!$C$13,"全仓清仓",IF(H8>C8,"卖出超额","正常定投")),"") | K8: =IFERROR(I8,"") | N8: =IFERROR(G8+M8,"") | O8: =IFERROR(O7+L8,"") | P8: =IFERROR(-L8,"")
C9: =IFERROR(参数配置!$C$6*(B9-$S$3),"") | F9: =IFERROR((D9-E9)/E9,"") | H9: =IFERROR(G9*D9,"") | I9: =IFERROR(IF(F9>=参数配置!$C$13,-H9,C9-H9),"") | J9: =IFERROR(IF(F9>=参数配置!$C$13,"全仓清仓",IF(H9>C9,"卖出超额","正常定投")),"") | K9: =IFERROR(I9,"") | N9: =IFERROR(G9+M9,"") | O9: =IFERROR(O8+L9,"") | P9: =IFERROR(-L9,"")
C10: =IFERROR(参数配置!$C$6*(B10-$S$3),"") | F10: =IFERROR((D10-E10)/E10,"") | H10: =IFERROR(G10*D10,"") | I10: =IFERROR(IF(F10>=参数配置!$C$13,-H10,C10-H10),"") | J10: =IFERROR(IF(F10>=参数配置!$C$13,"全仓清仓",IF(H10>C10,"卖出超额","正常定投")),"") | K10: =IFERROR(I10,"") | N10: =IFERROR(G10+M10,"") | O10: =IFERROR(O9+L10,"") | P10: =IFERROR(-L10,"")
C11: =IFERROR(参数配置!$C$6*(B11-$S$3),"") | F11: =IFERROR((D11-E11)/E11,"") | H11: =IFERROR(G11*D11,"") | I11: =IFERROR(IF(F11>=参数配置!$C$13,-H11,C11-H11),"") | J11: =IFERROR(IF(F11>=参数配置!$C$13,"全仓清仓",IF(H11>C11,"卖出超额","正常定投")),"") | K11: =IFERROR(I11,"") | N11: =IFERROR(G11+M11,"") | O11: =IFERROR(O10+L11,"") | P11: =IFERROR(-L11,"")
C12: =IFERROR(参数配置!$C$6*(B12-$S$3),"") | F12: =IFERROR((D12-E12)/E12,"") | H12: =IFERROR(G12*D12,"") | I12: =IFERROR(IF(F12>=参数配置!$C$13,-H12,C12-H12),"") | J12: =IFERROR(IF(F12>=参数配置!$C$13,"全仓清仓",IF(H12>C12,"卖出超额","正常定投")),"") | K12: =IFERROR(I12,"") | N12: =IFERROR(G12+M12,"") | O12: =IFERROR(O11+L12,"") | P12: =IFERROR(-L12,"")
C13: =IFERROR(参数配置!$C$6*(B13-$S$3),"") | F13: =IFERROR((D13-E13)/E13,"") | H13: =IFERROR(G13*D13,"") | I13: =IFERROR(IF(F13>=参数配置!$C$13,-H13,C13-H13),"") | J13: =IFERROR(IF(F13>=参数配置!$C$13,"全仓清仓",IF(H13>C13,"卖出超额","正常定投")),"") | K13: =IFERROR(I13,"") | N13: =IFERROR(G13+M13,"") | O13: =IFERROR(O12+L13,"") | P13: =IFERROR(-L13,"")
C14: =IFERROR(参数配置!$C$6*(B14-$S$3),"") | F14: =IFERROR((D14-E14)/E14,"") | H14: =IFERROR(G14*D14,"") | I14: =IFERROR(IF(F14>=参数配置!$C$13,-H14,C14-H14),"") | J14: =IFERROR(IF(F14>=参数配置!$C$13,"全仓清仓",IF(H14>C14,"卖出超额","正常定投")),"") | K14: =IFERROR(I14,"") | N14: =IFERROR(G14+M14,"") | O14: =IFERROR(O13+L14,"") | P14: =IFERROR(-L14,"")
C15: =IFERROR(参数配置!$C$6*(B15-$S$3),"") | F15: =IFERROR((D15-E15)/E15,"") | H15: =IFERROR(G15*D15,"") | I15: =IFERROR(IF(F15>=参数配置!$C$13,-H15,C15-H15),"") | J15: =IFERROR(IF(F15>=参数配置!$C$13,"全仓清仓",IF(H15>C15,"卖出超额","正常定投")),"") | K15: =IFERROR(I15,"") | N15: =IFERROR(G15+M15,"") | O15: =IFERROR(O14+L15,"") | P15: =IFERROR(-L15,"")
C16: =IFERROR(参数配置!$C$6*(B16-$S$3),"") | F16: =IFERROR((D16-E16)/E16,"") | H16: =IFERROR(G16*D16,"") | I16: =IFERROR(IF(F16>=参数配置!$C$13,-H16,C16-H16),"") | J16: =IFERROR(IF(F16>=参数配置!$C$13,"全仓清仓",IF(H16>C16,"卖出超额","正常定投")),"") | K16: =IFERROR(I16,"") | N16: =IFERROR(G16+M16,"") | O16: =IFERROR(O15+L16,"") | P16: =IFERROR(-L16,"")
C17: =IFERROR(参数配置!$C$6*(B17-$S$3),"") | F17: =IFERROR((D17-E17)/E17,"") | H17: =IFERROR(G17*D17,"") | I17: =IFERROR(IF(F17>=参数配置!$C$13,-H17,C17-H17),"") | J17: =IFERROR(IF(F17>=参数配置!$C$13,"全仓清仓",IF(H17>C17,"卖出超额","正常定投")),"") | K17: =IFERROR(I17,"") | N17: =IFERROR(G17+M17,"") | O17: =IFERROR(O16+L17,"") | P17: =IFERROR(-L17,"")
C18: =IFERROR(参数配置!$C$6*(B18-$S$3),"") | F18: =IFERROR((D18-E18)/E18,"") | H18: =IFERROR(G18*D18,"") | I18: =IFERROR(IF(F18>=参数配置!$C$13,-H18,C18-H18),"") | J18: =IFERROR(IF(F18>=参数配置!$C$13,"全仓清仓",IF(H18>C18,"卖出超额","正常定投")),"") | K18: =IFERROR(I18,"") | N18: =IFERROR(G18+M18,"") | O18: =IFERROR(O17+L18,"") | P18: =IFERROR(-L18,"")
C19: =IFERROR(参数配置!$C$6*(B19-$S$3),"") | F19: =IFERROR((D19-E19)/E19,"") | H19: =IFERROR(G19*D19,"") | I19: =IFERROR(IF(F19>=参数配置!$C$13,-H19,C19-H19),"") | J19: =IFERROR(IF(F19>=参数配置!$C$13,"全仓清仓",IF(H19>C19,"卖出超额","正常定投")),"") | K19: =IFERROR(I19,"") | N19: =IFERROR(G19+M19,"") | O19: =IFERROR(O18+L19,"") | P19: =IFERROR(-L19,"")
... C104: =IFERROR(参数配置!$C$6*(B104-$S$3),"") | F104: =IFERROR((D104-E104)/E104,"") | H104: =IFERROR(G104*D104,"") | I104: =IFERROR(IF(F104>=参数配置!$C$13,-H104,C104-H104),"") | J104: =IFERROR(IF(F104>=参数配置!$C$13,"全仓清仓",IF(H104>C104,"卖出超额","正常定投")),"") | K104: =IFERROR(I104,"") | N104: =IFERROR(G104+M104,"") | O104: =IFERROR(O103+L104,"") | P104: =IFERROR(-L104,"")

Sheet 恒生指数
A1: 恒生指数 ETF — 定投追踪记录
A2: 黄色=手动填写 绿色=自动计算 蓝色=建议参考（可覆盖）
A3: 手动填写 | B3: 自动计算 | C3: 建议参考 | R3: 期数偏移: | S3: 0
A4: 日期 | B4: 期数 | C4: 目标市值 | D4: 当前价格 | E4: 250日均线 | F4: 均线偏离度 | G4: 持仓份额 | H4: 持仓市值 | I4: 建议操作金额 | J4: 建议操作 | K4: 建议金额 | L4: 实际操作(元) | M4: 买卖份额 | N4: 操作后份额 | O4: 累计净投入 | P4: 储备金± | Q4: 备注
A5: 2026-04-24 | B5: 1 | C5: =IFERROR(参数配置!$C$7*(B5-$S$3),"") | D5: 1.526 | E5: 1.5383 | F5: =IFERROR((D5-E5)/E5,"") | G5: 0 | H5: =IFERROR(G5*D5,"") | I5: =IFERROR(IF(F5>=参数配置!$C$14,-H5,C5-H5),"") | J5: =IFERROR(IF(F5>=参数配置!$C$14,"全仓清仓",IF(H5>C5,"卖出超额","正常定投")),"") | K5: =IFERROR(I5,"") | L5: 457.8 | M5: 300 | N5: =IFERROR(G5+M5,"") | O5: =IFERROR(L5,"") | P5: =IFERROR(-L5,"")
A6: 2026-05-08 | B6: 2 | C6: =IFERROR(参数配置!$C$7*(B6-$S$3),"") | D6: 1.548 | E6: 1.5441 | F6: =IFERROR((D6-E6)/E6,"") | G6: 300 | H6: =IFERROR(G6*D6,"") | I6: =IFERROR(IF(F6>=参数配置!$C$14,-H6,C6-H6),"") | J6: =IFERROR(IF(F6>=参数配置!$C$14,"全仓清仓",IF(H6>C6,"卖出超额","正常定投")),"") | K6: =IFERROR(I6,"") | L6: 619.2 | M6: 400 | N6: =IFERROR(G6+M6,"") | O6: =IFERROR(O5+L6,"") | P6: =IFERROR(-L6,"")
A7: 2026-05-22 | B7: 3 | C7: =IFERROR(参数配置!$C$7*(B7-$S$3),"") | D7: 1.504 | E7: 1.5507 | F7: =IFERROR((D7-E7)/E7,"") | G7: 700 | H7: =IFERROR(G7*D7,"") | I7: =IFERROR(IF(F7>=参数配置!$C$14,-H7,C7-H7),"") | J7: =IFERROR(IF(F7>=参数配置!$C$14,"全仓清仓",IF(H7>C7,"卖出超额","正常定投")),"") | K7: =IFERROR(I7,"") | L7: 752 | M7: 500 | N7: =IFERROR(G7+M7,"") | O7: =IFERROR(O6+L7,"") | P7: =IFERROR(-L7,"")
C8: =IFERROR(参数配置!$C$7*(B8-$S$3),"") | F8: =IFERROR((D8-E8)/E8,"") | H8: =IFERROR(G8*D8,"") | I8: =IFERROR(IF(F8>=参数配置!$C$14,-H8,C8-H8),"") | J8: =IFERROR(IF(F8>=参数配置!$C$14,"全仓清仓",IF(H8>C8,"卖出超额","正常定投")),"") | K8: =IFERROR(I8,"") | N8: =IFERROR(G8+M8,"") | O8: =IFERROR(O7+L8,"") | P8: =IFERROR(-L8,"")
C9: =IFERROR(参数配置!$C$7*(B9-$S$3),"") | F9: =IFERROR((D9-E9)/E9,"") | H9: =IFERROR(G9*D9,"") | I9: =IFERROR(IF(F9>=参数配置!$C$14,-H9,C9-H9),"") | J9: =IFERROR(IF(F9>=参数配置!$C$14,"全仓清仓",IF(H9>C9,"卖出超额","正常定投")),"") | K9: =IFERROR(I9,"") | N9: =IFERROR(G9+M9,"") | O9: =IFERROR(O8+L9,"") | P9: =IFERROR(-L9,"")
C10: =IFERROR(参数配置!$C$7*(B10-$S$3),"") | F10: =IFERROR((D10-E10)/E10,"") | H10: =IFERROR(G10*D10,"") | I10: =IFERROR(IF(F10>=参数配置!$C$14,-H10,C10-H10),"") | J10: =IFERROR(IF(F10>=参数配置!$C$14,"全仓清仓",IF(H10>C10,"卖出超额","正常定投")),"") | K10: =IFERROR(I10,"") | N10: =IFERROR(G10+M10,"") | O10: =IFERROR(O9+L10,"") | P10: =IFERROR(-L10,"")
C11: =IFERROR(参数配置!$C$7*(B11-$S$3),"") | F11: =IFERROR((D11-E11)/E11,"") | H11: =IFERROR(G11*D11,"") | I11: =IFERROR(IF(F11>=参数配置!$C$14,-H11,C11-H11),"") | J11: =IFERROR(IF(F11>=参数配置!$C$14,"全仓清仓",IF(H11>C11,"卖出超额","正常定投")),"") | K11: =IFERROR(I11,"") | N11: =IFERROR(G11+M11,"") | O11: =IFERROR(O10+L11,"") | P11: =IFERROR(-L11,"")
C12: =IFERROR(参数配置!$C$7*(B12-$S$3),"") | F12: =IFERROR((D12-E12)/E12,"") | H12: =IFERROR(G12*D12,"") | I12: =IFERROR(IF(F12>=参数配置!$C$14,-H12,C12-H12),"") | J12: =IFERROR(IF(F12>=参数配置!$C$14,"全仓清仓",IF(H12>C12,"卖出超额","正常定投")),"") | K12: =IFERROR(I12,"") | N12: =IFERROR(G12+M12,"") | O12: =IFERROR(O11+L12,"") | P12: =IFERROR(-L12,"")
C13: =IFERROR(参数配置!$C$7*(B13-$S$3),"") | F13: =IFERROR((D13-E13)/E13,"") | H13: =IFERROR(G13*D13,"") | I13: =IFERROR(IF(F13>=参数配置!$C$14,-H13,C13-H13),"") | J13: =IFERROR(IF(F13>=参数配置!$C$14,"全仓清仓",IF(H13>C13,"卖出超额","正常定投")),"") | K13: =IFERROR(I13,"") | N13: =IFERROR(G13+M13,"") | O13: =IFERROR(O12+L13,"") | P13: =IFERROR(-L13,"")
C14: =IFERROR(参数配置!$C$7*(B14-$S$3),"") | F14: =IFERROR((D14-E14)/E14,"") | H14: =IFERROR(G14*D14,"") | I14: =IFERROR(IF(F14>=参数配置!$C$14,-H14,C14-H14),"") | J14: =IFERROR(IF(F14>=参数配置!$C$14,"全仓清仓",IF(H14>C14,"卖出超额","正常定投")),"") | K14: =IFERROR(I14,"") | N14: =IFERROR(G14+M14,"") | O14: =IFERROR(O13+L14,"") | P14: =IFERROR(-L14,"")
C15: =IFERROR(参数配置!$C$7*(B15-$S$3),"") | F15: =IFERROR((D15-E15)/E15,"") | H15: =IFERROR(G15*D15,"") | I15: =IFERROR(IF(F15>=参数配置!$C$14,-H15,C15-H15),"") | J15: =IFERROR(IF(F15>=参数配置!$C$14,"全仓清仓",IF(H15>C15,"卖出超额","正常定投")),"") | K15: =IFERROR(I15,"") | N15: =IFERROR(G15+M15,"") | O15: =IFERROR(O14+L15,"") | P15: =IFERROR(-L15,"")
C16: =IFERROR(参数配置!$C$7*(B16-$S$3),"") | F16: =IFERROR((D16-E16)/E16,"") | H16: =IFERROR(G16*D16,"") | I16: =IFERROR(IF(F16>=参数配置!$C$14,-H16,C16-H16),"") | J16: =IFERROR(IF(F16>=参数配置!$C$14,"全仓清仓",IF(H16>C16,"卖出超额","正常定投")),"") | K16: =IFERROR(I16,"") | N16: =IFERROR(G16+M16,"") | O16: =IFERROR(O15+L16,"") | P16: =IFERROR(-L16,"")
C17: =IFERROR(参数配置!$C$7*(B17-$S$3),"") | F17: =IFERROR((D17-E17)/E17,"") | H17: =IFERROR(G17*D17,"") | I17: =IFERROR(IF(F17>=参数配置!$C$14,-H17,C17-H17),"") | J17: =IFERROR(IF(F17>=参数配置!$C$14,"全仓清仓",IF(H17>C17,"卖出超额","正常定投")),"") | K17: =IFERROR(I17,"") | N17: =IFERROR(G17+M17,"") | O17: =IFERROR(O16+L17,"") | P17: =IFERROR(-L17,"")
C18: =IFERROR(参数配置!$C$7*(B18-$S$3),"") | F18: =IFERROR((D18-E18)/E18,"") | H18: =IFERROR(G18*D18,"") | I18: =IFERROR(IF(F18>=参数配置!$C$14,-H18,C18-H18),"") | J18: =IFERROR(IF(F18>=参数配置!$C$14,"全仓清仓",IF(H18>C18,"卖出超额","正常定投")),"") | K18: =IFERROR(I18,"") | N18: =IFERROR(G18+M18,"") | O18: =IFERROR(O17+L18,"") | P18: =IFERROR(-L18,"")
C19: =IFERROR(参数配置!$C$7*(B19-$S$3),"") | F19: =IFERROR((D19-E19)/E19,"") | H19: =IFERROR(G19*D19,"") | I19: =IFERROR(IF(F19>=参数配置!$C$14,-H19,C19-H19),"") | J19: =IFERROR(IF(F19>=参数配置!$C$14,"全仓清仓",IF(H19>C19,"卖出超额","正常定投")),"") | K19: =IFERROR(I19,"") | N19: =IFERROR(G19+M19,"") | O19: =IFERROR(O18+L19,"") | P19: =IFERROR(-L19,"")
... C104: =IFERROR(参数配置!$C$7*(B104-$S$3),"") | F104: =IFERROR((D104-E104)/E104,"") | H104: =IFERROR(G104*D104,"") | I104: =IFERROR(IF(F104>=参数配置!$C$14,-H104,C104-H104),"") | J104: =IFERROR(IF(F104>=参数配置!$C$14,"全仓清仓",IF(H104>C104,"卖出超额","正常定投")),"") | K104: =IFERROR(I104,"") | N104: =IFERROR(G104+M104,"") | O104: =IFERROR(O103+L104,"") | P104: =IFERROR(-L104,"")

Sheet 纳指100
A1: 纳指100 ETF — 定投追踪记录
A2: 黄色=手动填写 绿色=自动计算 蓝色=建议参考（可覆盖）
A3: 手动填写 | B3: 自动计算 | C3: 建议参考 | R3: 期数偏移: | S3: 0
A4: 日期 | B4: 期数 | C4: 目标市值 | D4: 当前价格 | E4: 250日均线 | F4: 均线偏离度 | G4: 持仓份额 | H4: 持仓市值 | I4: 建议操作金额 | J4: 建议操作 | K4: 建议金额 | L4: 实际操作(元) | M4: 买卖份额 | N4: 操作后份额 | O4: 累计净投入 | P4: 储备金± | Q4: 备注
A5: 2026-04-24 | B5: 1 | C5: =IFERROR(参数配置!$C$8*(B5-$S$3),"") | D5: 1.904 | E5: 1.7458 | F5: =IFERROR((D5-E5)/E5,"") | G5: 0 | H5: =IFERROR(G5*D5,"") | I5: =IFERROR(IF(F5>=参数配置!$C$15,-H5,C5-H5),"") | J5: =IFERROR(IF(F5>=参数配置!$C$15,"全仓清仓",IF(H5>C5,"卖出超额","正常定投")),"") | K5: =IFERROR(I5,"") | L5: 2284.8 | M5: 1200 | N5: =IFERROR(G5+M5,"") | O5: =IFERROR(L5,"") | P5: =IFERROR(-L5,"")
A6: 2026-05-08 | B6: 2 | C6: =IFERROR(参数配置!$C$8*(B6-$S$3),"") | D6: 2.046 | E6: 1.7612 | F6: =IFERROR((D6-E6)/E6,"") | G6: 1200 | H6: =IFERROR(G6*D6,"") | I6: =IFERROR(IF(F6>=参数配置!$C$15,-H6,C6-H6),"") | J6: =IFERROR(IF(F6>=参数配置!$C$15,"全仓清仓",IF(H6>C6,"卖出超额","正常定投")),"") | K6: =IFERROR(I6,"") | L6: 2250.6 | M6: 1100 | N6: =IFERROR(G6+M6,"") | O6: =IFERROR(O5+L6,"") | P6: =IFERROR(-L6,"")
A7: 2026-05-22 | B7: 3 | C7: =IFERROR(参数配置!$C$8*(B7-$S$3),"") | D7: 2.124 | E7: 1.7868 | F7: =IFERROR((D7-E7)/E7,"") | G7: 2300 | H7: =IFERROR(G7*D7,"") | I7: =IFERROR(IF(F7>=参数配置!$C$15,-H7,C7-H7),"") | J7: =IFERROR(IF(F7>=参数配置!$C$15,"全仓清仓",IF(H7>C7,"卖出超额","正常定投")),"") | K7: =IFERROR(I7,"") | L7: 2336.4 | M7: 1100 | N7: =IFERROR(G7+M7,"") | O7: =IFERROR(O6+L7,"") | P7: =IFERROR(-L7,"")
C8: =IFERROR(参数配置!$C$8*(B8-$S$3),"") | F8: =IFERROR((D8-E8)/E8,"") | H8: =IFERROR(G8*D8,"") | I8: =IFERROR(IF(F8>=参数配置!$C$15,-H8,C8-H8),"") | J8: =IFERROR(IF(F8>=参数配置!$C$15,"全仓清仓",IF(H8>C8,"卖出超额","正常定投")),"") | K8: =IFERROR(I8,"") | N8: =IFERROR(G8+M8,"") | O8: =IFERROR(O7+L8,"") | P8: =IFERROR(-L8,"")
C9: =IFERROR(参数配置!$C$8*(B9-$S$3),"") | F9: =IFERROR((D9-E9)/E9,"") | H9: =IFERROR(G9*D9,"") | I9: =IFERROR(IF(F9>=参数配置!$C$15,-H9,C9-H9),"") | J9: =IFERROR(IF(F9>=参数配置!$C$15,"全仓清仓",IF(H9>C9,"卖出超额","正常定投")),"") | K9: =IFERROR(I9,"") | N9: =IFERROR(G9+M9,"") | O9: =IFERROR(O8+L9,"") | P9: =IFERROR(-L9,"")
C10: =IFERROR(参数配置!$C$8*(B10-$S$3),"") | F10: =IFERROR((D10-E10)/E10,"") | H10: =IFERROR(G10*D10,"") | I10: =IFERROR(IF(F10>=参数配置!$C$15,-H10,C10-H10),"") | J10: =IFERROR(IF(F10>=参数配置!$C$15,"全仓清仓",IF(H10>C10,"卖出超额","正常定投")),"") | K10: =IFERROR(I10,"") | N10: =IFERROR(G10+M10,"") | O10: =IFERROR(O9+L10,"") | P10: =IFERROR(-L10,"")
C11: =IFERROR(参数配置!$C$8*(B11-$S$3),"") | F11: =IFERROR((D11-E11)/E11,"") | H11: =IFERROR(G11*D11,"") | I11: =IFERROR(IF(F11>=参数配置!$C$15,-H11,C11-H11),"") | J11: =IFERROR(IF(F11>=参数配置!$C$15,"全仓清仓",IF(H11>C11,"卖出超额","正常定投")),"") | K11: =IFERROR(I11,"") | N11: =IFERROR(G11+M11,"") | O11: =IFERROR(O10+L11,"") | P11: =IFERROR(-L11,"")
C12: =IFERROR(参数配置!$C$8*(B12-$S$3),"") | F12: =IFERROR((D12-E12)/E12,"") | H12: =IFERROR(G12*D12,"") | I12: =IFERROR(IF(F12>=参数配置!$C$15,-H12,C12-H12),"") | J12: =IFERROR(IF(F12>=参数配置!$C$15,"全仓清仓",IF(H12>C12,"卖出超额","正常定投")),"") | K12: =IFERROR(I12,"") | N12: =IFERROR(G12+M12,"") | O12: =IFERROR(O11+L12,"") | P12: =IFERROR(-L12,"")
C13: =IFERROR(参数配置!$C$8*(B13-$S$3),"") | F13: =IFERROR((D13-E13)/E13,"") | H13: =IFERROR(G13*D13,"") | I13: =IFERROR(IF(F13>=参数配置!$C$15,-H13,C13-H13),"") | J13: =IFERROR(IF(F13>=参数配置!$C$15,"全仓清仓",IF(H13>C13,"卖出超额","正常定投")),"") | K13: =IFERROR(I13,"") | N13: =IFERROR(G13+M13,"") | O13: =IFERROR(O12+L13,"") | P13: =IFERROR(-L13,"")
C14: =IFERROR(参数配置!$C$8*(B14-$S$3),"") | F14: =IFERROR((D14-E14)/E14,"") | H14: =IFERROR(G14*D14,"") | I14: =IFERROR(IF(F14>=参数配置!$C$15,-H14,C14-H14),"") | J14: =IFERROR(IF(F14>=参数配置!$C$15,"全仓清仓",IF(H14>C14,"卖出超额","正常定投")),"") | K14: =IFERROR(I14,"") | N14: =IFERROR(G14+M14,"") | O14: =IFERROR(O13+L14,"") | P14: =IFERROR(-L14,"")
C15: =IFERROR(参数配置!$C$8*(B15-$S$3),"") | F15: =IFERROR((D15-E15)/E15,"") | H15: =IFERROR(G15*D15,"") | I15: =IFERROR(IF(F15>=参数配置!$C$15,-H15,C15-H15),"") | J15: =IFERROR(IF(F15>=参数配置!$C$15,"全仓清仓",IF(H15>C15,"卖出超额","正常定投")),"") | K15: =IFERROR(I15,"") | N15: =IFERROR(G15+M15,"") | O15: =IFERROR(O14+L15,"") | P15: =IFERROR(-L15,"")
C16: =IFERROR(参数配置!$C$8*(B16-$S$3),"") | F16: =IFERROR((D16-E16)/E16,"") | H16: =IFERROR(G16*D16,"") | I16: =IFERROR(IF(F16>=参数配置!$C$15,-H16,C16-H16),"") | J16: =IFERROR(IF(F16>=参数配置!$C$15,"全仓清仓",IF(H16>C16,"卖出超额","正常定投")),"") | K16: =IFERROR(I16,"") | N16: =IFERROR(G16+M16,"") | O16: =IFERROR(O15+L16,"") | P16: =IFERROR(-L16,"")
C17: =IFERROR(参数配置!$C$8*(B17-$S$3),"") | F17: =IFERROR((D17-E17)/E17,"") | H17: =IFERROR(G17*D17,"") | I17: =IFERROR(IF(F17>=参数配置!$C$15,-H17,C17-H17),"") | J17: =IFERROR(IF(F17>=参数配置!$C$15,"全仓清仓",IF(H17>C17,"卖出超额","正常定投")),"") | K17: =IFERROR(I17,"") | N17: =IFERROR(G17+M17,"") | O17: =IFERROR(O16+L17,"") | P17: =IFERROR(-L17,"")
C18: =IFERROR(参数配置!$C$8*(B18-$S$3),"") | F18: =IFERROR((D18-E18)/E18,"") | H18: =IFERROR(G18*D18,"") | I18: =IFERROR(IF(F18>=参数配置!$C$15,-H18,C18-H18),"") | J18: =IFERROR(IF(F18>=参数配置!$C$15,"全仓清仓",IF(H18>C18,"卖出超额","正常定投")),"") | K18: =IFERROR(I18,"") | N18: =IFERROR(G18+M18,"") | O18: =IFERROR(O17+L18,"") | P18: =IFERROR(-L18,"")
C19: =IFERROR(参数配置!$C$8*(B19-$S$3),"") | F19: =IFERROR((D19-E19)/E19,"") | H19: =IFERROR(G19*D19,"") | I19: =IFERROR(IF(F19>=参数配置!$C$15,-H19,C19-H19),"") | J19: =IFERROR(IF(F19>=参数配置!$C$15,"全仓清仓",IF(H19>C19,"卖出超额","正常定投")),"") | K19: =IFERROR(I19,"") | N19: =IFERROR(G19+M19,"") | O19: =IFERROR(O18+L19,"") | P19: =IFERROR(-L19,"")
... C104: =IFERROR(参数配置!$C$8*(B104-$S$3),"") | F104: =IFERROR((D104-E104)/E104,"") | H104: =IFERROR(G104*D104,"") | I104: =IFERROR(IF(F104>=参数配置!$C$15,-H104,C104-H104),"") | J104: =IFERROR(IF(F104>=参数配置!$C$15,"全仓清仓",IF(H104>C104,"卖出超额","正常定投")),"") | K104: =IFERROR(I104,"") | N104: =IFERROR(G104+M104,"") | O104: =IFERROR(O103+L104,"") | P104: =IFERROR(-L104,"")
